luka/__init__.py
luka/styling/__init__.py
luka/styling/_print.py
luka/styling/constants.py
luka-0.0.1.dist-info/LICENSE
luka-0.0.1.dist-info/METADATA
luka-0.0.1.dist-info/WHEEL
luka-0.0.1.dist-info/top_level.txt
luka-0.0.1.dist-info/RECORD
