Metadata-Version: 2.1
Name: luka
Version: 0.0.1
Summary: Personal Package
Author-email: Hisham Ali <hishamali98@gmail.com>
License: MIT License
Keywords: Luka,Modric
Classifier: Programming Language :: Python :: 3
Classifier: License :: OSI Approved :: MIT License
Classifier: Operating System :: OS Independent
Requires-Python: >=3.7
License-File: LICENSE
